{
   "sidebarNavigation": [
      {
         "title": {
            "en-US": "Store",
            "pt-BR": "Loja",
            "es-ES": "almacenar"
         },
         "url": "/"
      },
      {
         "title": {
            "en-US": "Library",
            "pt-BR": "Biblioteca",
            "es-ES": "Biblioteca"
         },
         "url": "/library"
      },
      {
         "title": {
            "en-US": "News",
            "pt-BR": "Notícias",
            "es-ES": "Noticias"
         },
         "url": "/news"
      },
      {
         "title": {
            "en-US": "Settings",
            "pt-BR": "Configurações",
            "es-ES": "Ajustes"
         },
         "url": "/settings"
      }
   ],
   "genresData": {
      "en-US": [
         "Action",
         "Adventure",
         "Role-Playing (RPG)",
         "Strategy",
         "Simulation",
         "Sports",
         "Racing",
         "Fighting",
         "Puzzle",
         "Horror"
      ],
      "pt-BR": [
         "Ação",
         "Aventura",
         "RPG (Role-Playing Game)",
         "Estratégia",
         "Simulação",
         "Esportes",
         "Corrida",
         "Luta",
         "Quebra-Cabeça",
         "Terror"
      ],
      "es-ES": [
         "Acción",
         "Aventura",
         "Rol (RPG)",
         "Estrategia",
         "Simulación",
         "Deportes",
         "Carreras",
         "Lucha",
         "Rompecabezas",
         "Terror"
      ]
   },
   "dropdownOptions": [
      {
         "title": {
            "en-US": "Profile",
            "pt-BR": "Perfil",
            "es-ES": "Perfil"
         },
         "url": "/profile"
      },
      {
         "title": {
            "en-US": "Library",
            "pt-BR": "Biblioteca",
            "es-ES": "Biblioteca"
         },
         "url": "/library"
      },
      {
         "title": {
            "en-US": "WishList",
            "pt-BR": "Lista de desejos",
            "es-ES": "Lista de deseos"
         },
         "url": "/wishlist"
      },
      {
         "title": {
            "en-US": "Sign Out",
            "pt-BR": "Sair",
            "es-ES": "Salir"
         },
         "url": "/"
      }
   ],
   "footer": [
      {
         "title": {
            "en-US": "Customer Service",
            "pt-BR": "Atendimento ao cliente",
            "es-ES": "Servicio al cliente"
         },
         "itens": [
            {
               "en-US": "Contact Us",
               "pt-BR": "Fale conosco",
               "es-ES": "Contáctenos",
               "url": "/"
            },
            {
               "en-US": "Return Policy",
               "pt-BR": "Política de devolução",
               "es-ES": "Política de devoluciones",
               "url": "/"
            },
            {
               "en-US": "Payment Methods",
               "pt-BR": "Métodos de pagamento",
               "es-ES": "Métodos de pago",
               "url": "/"
            }
         ]
      },
      {
         "title": {
            "en-US": "Support",
            "pt-BR": "Suporte",
            "es-ES": "Soporte"
         },
         "itens": [
            {
               "en-US": "Returns",
               "pt-BR": "Devolução",
               "es-ES": "Devoluciones",
               "url": "/"
            }
         ]
      },
      {
         "title": {
            "en-US": "Payment Rules",
            "pt-BR": "Regras de pagamento",
            "es-ES": "Reglas de pago"
         },
         "itens": [
            {
               "en-US": "Credit and Debit Card",
               "pt-BR": "Cartão de crédito e débito",
               "es-ES": "Tarjeta de crédito y débito",
               "url": "/"
            },
            {
               "en-US": "Gift Card",
               "pt-BR": "Cartão presente",
               "es-ES": "Tarjeta de regalo",
               "url": "/"
            },
            {
               "en-US": "Pix",
               "pt-BR": "Pix",
               "es-ES": "Pix",
               "url": "/"
            }
         ]
      }
   ]
}
